[
    {
        "step": 0,
        "LE_instances": 0,
        "LE_relative": 0.0,
        "accuracy": 0.91
    },
    {
        "step": 1,
        "LE_instances": 2,
        "LE_relative": 0.02,
        "accuracy": 0.92
    },
    {
        "step": 2,
        "LE_instances": 4,
        "LE_relative": 0.04,
        "accuracy": 0.89
    },
    {
        "step": 3,
        "LE_instances": 6,
        "LE_relative": 0.06,
        "accuracy": 0.9
    },
    {
        "step": 4,
        "LE_instances": 8,
        "LE_relative": 0.08,
        "accuracy": 0.85
    },
    {
        "step": 5,
        "LE_instances": 10,
        "LE_relative": 0.1,
        "accuracy": 0.86
    },
    {
        "step": 6,
        "LE_instances": 12,
        "LE_relative": 0.12,
        "accuracy": 0.82
    },
    {
        "step": 7,
        "LE_instances": 14,
        "LE_relative": 0.14,
        "accuracy": 0.8
    },
    {
        "step": 8,
        "LE_instances": 16,
        "LE_relative": 0.16,
        "accuracy": 0.82
    },
    {
        "step": 9,
        "LE_instances": 18,
        "LE_relative": 0.18,
        "accuracy": 0.83
    },
    {
        "step": 10,
        "LE_instances": 20,
        "LE_relative": 0.2,
        "accuracy": 0.82
    },
    {
        "step": 11,
        "LE_instances": 22,
        "LE_relative": 0.22,
        "accuracy": 0.82
    },
    {
        "step": 12,
        "LE_instances": 24,
        "LE_relative": 0.24,
        "accuracy": 0.78
    },
    {
        "step": 13,
        "LE_instances": 26,
        "LE_relative": 0.26,
        "accuracy": 0.75
    },
    {
        "step": 14,
        "LE_instances": 28,
        "LE_relative": 0.28,
        "accuracy": 0.74
    },
    {
        "step": 15,
        "LE_instances": 30,
        "LE_relative": 0.3,
        "accuracy": 0.74
    },
    {
        "step": 16,
        "LE_instances": 32,
        "LE_relative": 0.32,
        "accuracy": 0.72
    },
    {
        "step": 17,
        "LE_instances": 34,
        "LE_relative": 0.34,
        "accuracy": 0.71
    },
    {
        "step": 18,
        "LE_instances": 36,
        "LE_relative": 0.36,
        "accuracy": 0.71
    },
    {
        "step": 19,
        "LE_instances": 38,
        "LE_relative": 0.38,
        "accuracy": 0.69
    },
    {
        "step": 20,
        "LE_instances": 40,
        "LE_relative": 0.4,
        "accuracy": 0.72
    },
    {
        "step": 21,
        "LE_instances": 42,
        "LE_relative": 0.42,
        "accuracy": 0.65
    },
    {
        "step": 22,
        "LE_instances": 44,
        "LE_relative": 0.44,
        "accuracy": 0.63
    },
    {
        "step": 23,
        "LE_instances": 46,
        "LE_relative": 0.46,
        "accuracy": 0.56
    },
    {
        "step": 24,
        "LE_instances": 48,
        "LE_relative": 0.48,
        "accuracy": 0.54
    },
    {
        "step": 25,
        "LE_instances": 50,
        "LE_relative": 0.5,
        "accuracy": 0.56
    },
    {
        "step": 26,
        "LE_instances": 52,
        "LE_relative": 0.52,
        "accuracy": 0.55
    },
    {
        "step": 27,
        "LE_instances": 54,
        "LE_relative": 0.54,
        "accuracy": 0.49
    },
    {
        "step": 28,
        "LE_instances": 56,
        "LE_relative": 0.56,
        "accuracy": 0.5
    },
    {
        "step": 29,
        "LE_instances": 58,
        "LE_relative": 0.58,
        "accuracy": 0.46
    },
    {
        "step": 30,
        "LE_instances": 60,
        "LE_relative": 0.6,
        "accuracy": 0.38
    },
    {
        "step": 31,
        "LE_instances": 62,
        "LE_relative": 0.62,
        "accuracy": 0.39
    },
    {
        "step": 32,
        "LE_instances": 64,
        "LE_relative": 0.64,
        "accuracy": 0.37
    },
    {
        "step": 33,
        "LE_instances": 66,
        "LE_relative": 0.66,
        "accuracy": 0.31
    },
    {
        "step": 34,
        "LE_instances": 68,
        "LE_relative": 0.68,
        "accuracy": 0.34
    },
    {
        "step": 35,
        "LE_instances": 70,
        "LE_relative": 0.7,
        "accuracy": 0.29
    },
    {
        "step": 36,
        "LE_instances": 72,
        "LE_relative": 0.72,
        "accuracy": 0.26
    },
    {
        "step": 37,
        "LE_instances": 74,
        "LE_relative": 0.74,
        "accuracy": 0.23
    },
    {
        "step": 38,
        "LE_instances": 76,
        "LE_relative": 0.76,
        "accuracy": 0.24
    },
    {
        "step": 39,
        "LE_instances": 78,
        "LE_relative": 0.78,
        "accuracy": 0.22
    },
    {
        "step": 40,
        "LE_instances": 80,
        "LE_relative": 0.8,
        "accuracy": 0.23
    },
    {
        "step": 41,
        "LE_instances": 82,
        "LE_relative": 0.82,
        "accuracy": 0.18
    },
    {
        "step": 42,
        "LE_instances": 84,
        "LE_relative": 0.84,
        "accuracy": 0.13
    },
    {
        "step": 43,
        "LE_instances": 86,
        "LE_relative": 0.86,
        "accuracy": 0.14
    },
    {
        "step": 44,
        "LE_instances": 88,
        "LE_relative": 0.88,
        "accuracy": 0.11
    },
    {
        "step": 45,
        "LE_instances": 90,
        "LE_relative": 0.9,
        "accuracy": 0.1
    }
]