[
    {
        "step": 1,
        "LE_instances": 0,
        "LE_relative": 0.0,
        "accuracy": 0.933333,
        "train_time": 0.7005,
        "eval_time": 0.9695
    },
    {
        "step": 2,
        "LE_instances": 1,
        "LE_relative": 0.016666666666666666,
        "accuracy": 0.9,
        "train_time": 0.8204,
        "eval_time": 0.9497
    },
    {
        "step": 3,
        "LE_instances": 2,
        "LE_relative": 0.03333333333333333,
        "accuracy": 0.833333,
        "train_time": 0.7925,
        "eval_time": 1.0257
    },
    {
        "step": 4,
        "LE_instances": 3,
        "LE_relative": 0.05,
        "accuracy": 0.833333,
        "train_time": 0.7851,
        "eval_time": 1.0268
    },
    {
        "step": 5,
        "LE_instances": 4,
        "LE_relative": 0.06666666666666667,
        "accuracy": 0.816667,
        "train_time": 0.7821,
        "eval_time": 0.9857
    },
    {
        "step": 6,
        "LE_instances": 5,
        "LE_relative": 0.08333333333333333,
        "accuracy": 0.816667,
        "train_time": 0.7822,
        "eval_time": 1.0563
    },
    {
        "step": 7,
        "LE_instances": 6,
        "LE_relative": 0.09999999999999999,
        "accuracy": 0.8,
        "train_time": 0.7728,
        "eval_time": 1.0102
    },
    {
        "step": 8,
        "LE_instances": 7,
        "LE_relative": 0.11666666666666665,
        "accuracy": 0.8,
        "train_time": 0.835,
        "eval_time": 0.9669
    },
    {
        "step": 9,
        "LE_instances": 8,
        "LE_relative": 0.13333333333333333,
        "accuracy": 0.8,
        "train_time": 0.8207,
        "eval_time": 0.995
    },
    {
        "step": 10,
        "LE_instances": 9,
        "LE_relative": 0.15,
        "accuracy": 0.8,
        "train_time": 0.7582,
        "eval_time": 1.0206
    },
    {
        "step": 11,
        "LE_instances": 10,
        "LE_relative": 0.16666666666666666,
        "accuracy": 0.8,
        "train_time": 0.7831,
        "eval_time": 1.0137
    },
    {
        "step": 12,
        "LE_instances": 11,
        "LE_relative": 0.18333333333333332,
        "accuracy": 0.783333,
        "train_time": 0.777,
        "eval_time": 1.0466
    },
    {
        "step": 13,
        "LE_instances": 12,
        "LE_relative": 0.19999999999999998,
        "accuracy": 0.8,
        "train_time": 0.7823,
        "eval_time": 0.9715
    },
    {
        "step": 14,
        "LE_instances": 13,
        "LE_relative": 0.21666666666666665,
        "accuracy": 0.733333,
        "train_time": 0.7831,
        "eval_time": 0.9698
    },
    {
        "step": 15,
        "LE_instances": 14,
        "LE_relative": 0.2333333333333333,
        "accuracy": 0.716667,
        "train_time": 0.7724,
        "eval_time": 0.9678
    },
    {
        "step": 16,
        "LE_instances": 15,
        "LE_relative": 0.24999999999999997,
        "accuracy": 0.683333,
        "train_time": 0.7893,
        "eval_time": 0.9635
    },
    {
        "step": 17,
        "LE_instances": 16,
        "LE_relative": 0.26666666666666666,
        "accuracy": 0.666667,
        "train_time": 0.7704,
        "eval_time": 0.9873
    },
    {
        "step": 18,
        "LE_instances": 17,
        "LE_relative": 0.2833333333333333,
        "accuracy": 0.683333,
        "train_time": 0.7892,
        "eval_time": 1.0184
    },
    {
        "step": 19,
        "LE_instances": 18,
        "LE_relative": 0.3,
        "accuracy": 0.633333,
        "train_time": 0.8054,
        "eval_time": 0.9558
    },
    {
        "step": 20,
        "LE_instances": 19,
        "LE_relative": 0.31666666666666665,
        "accuracy": 0.633333,
        "train_time": 0.7959,
        "eval_time": 0.9593
    },
    {
        "step": 21,
        "LE_instances": 20,
        "LE_relative": 0.3333333333333333,
        "accuracy": 0.65,
        "train_time": 0.8181,
        "eval_time": 0.9805
    },
    {
        "step": 22,
        "LE_instances": 21,
        "LE_relative": 0.35,
        "accuracy": 0.633333,
        "train_time": 0.7711,
        "eval_time": 0.9857
    },
    {
        "step": 23,
        "LE_instances": 22,
        "LE_relative": 0.36666666666666664,
        "accuracy": 0.633333,
        "train_time": 0.7882,
        "eval_time": 0.9707
    },
    {
        "step": 24,
        "LE_instances": 23,
        "LE_relative": 0.3833333333333333,
        "accuracy": 0.6,
        "train_time": 0.7812,
        "eval_time": 0.9834
    },
    {
        "step": 25,
        "LE_instances": 24,
        "LE_relative": 0.39999999999999997,
        "accuracy": 0.583333,
        "train_time": 0.8061,
        "eval_time": 0.9853
    },
    {
        "step": 26,
        "LE_instances": 25,
        "LE_relative": 0.41666666666666663,
        "accuracy": 0.566667,
        "train_time": 0.7738,
        "eval_time": 0.9972
    },
    {
        "step": 27,
        "LE_instances": 26,
        "LE_relative": 0.4333333333333333,
        "accuracy": 0.6,
        "train_time": 0.8095,
        "eval_time": 1.0054
    },
    {
        "step": 28,
        "LE_instances": 27,
        "LE_relative": 0.44999999999999996,
        "accuracy": 0.583333,
        "train_time": 0.7906,
        "eval_time": 0.955
    },
    {
        "step": 29,
        "LE_instances": 28,
        "LE_relative": 0.4666666666666666,
        "accuracy": 0.583333,
        "train_time": 0.8184,
        "eval_time": 1.0564
    },
    {
        "step": 30,
        "LE_instances": 29,
        "LE_relative": 0.4833333333333333,
        "accuracy": 0.533333,
        "train_time": 0.7862,
        "eval_time": 1.0126
    },
    {
        "step": 31,
        "LE_instances": 30,
        "LE_relative": 0.49999999999999994,
        "accuracy": 0.533333,
        "train_time": 0.8264,
        "eval_time": 0.9904
    },
    {
        "step": 32,
        "LE_instances": 31,
        "LE_relative": 0.5166666666666666,
        "accuracy": 0.5,
        "train_time": 0.7742,
        "eval_time": 1.011
    },
    {
        "step": 33,
        "LE_instances": 32,
        "LE_relative": 0.5333333333333333,
        "accuracy": 0.5,
        "train_time": 0.788,
        "eval_time": 0.9877
    },
    {
        "step": 34,
        "LE_instances": 33,
        "LE_relative": 0.55,
        "accuracy": 0.483333,
        "train_time": 0.7696,
        "eval_time": 0.986
    },
    {
        "step": 35,
        "LE_instances": 34,
        "LE_relative": 0.5666666666666668,
        "accuracy": 0.45,
        "train_time": 0.7834,
        "eval_time": 0.9543
    },
    {
        "step": 36,
        "LE_instances": 35,
        "LE_relative": 0.5833333333333335,
        "accuracy": 0.466667,
        "train_time": 0.7869,
        "eval_time": 0.9704
    },
    {
        "step": 37,
        "LE_instances": 36,
        "LE_relative": 0.6000000000000002,
        "accuracy": 0.416667,
        "train_time": 0.7914,
        "eval_time": 0.9836
    },
    {
        "step": 38,
        "LE_instances": 37,
        "LE_relative": 0.6166666666666669,
        "accuracy": 0.383333,
        "train_time": 0.7797,
        "eval_time": 0.9719
    },
    {
        "step": 39,
        "LE_instances": 38,
        "LE_relative": 0.6333333333333336,
        "accuracy": 0.366667,
        "train_time": 0.8438,
        "eval_time": 0.9986
    },
    {
        "step": 40,
        "LE_instances": 39,
        "LE_relative": 0.6500000000000004,
        "accuracy": 0.333333,
        "train_time": 0.7917,
        "eval_time": 1.0222
    },
    {
        "step": 41,
        "LE_instances": 40,
        "LE_relative": 0.6666666666666671,
        "accuracy": 0.366667,
        "train_time": 0.82,
        "eval_time": 1.023
    },
    {
        "step": 42,
        "LE_instances": 41,
        "LE_relative": 0.6833333333333338,
        "accuracy": 0.366667,
        "train_time": 0.7911,
        "eval_time": 0.981
    },
    {
        "step": 43,
        "LE_instances": 42,
        "LE_relative": 0.7000000000000005,
        "accuracy": 0.35,
        "train_time": 0.8068,
        "eval_time": 0.9699
    },
    {
        "step": 44,
        "LE_instances": 43,
        "LE_relative": 0.7166666666666672,
        "accuracy": 0.333333,
        "train_time": 0.7633,
        "eval_time": 0.9989
    },
    {
        "step": 45,
        "LE_instances": 44,
        "LE_relative": 0.733333333333334,
        "accuracy": 0.333333,
        "train_time": 0.8911,
        "eval_time": 0.9824
    },
    {
        "step": 46,
        "LE_instances": 45,
        "LE_relative": 0.7500000000000007,
        "accuracy": 0.333333,
        "train_time": 0.7729,
        "eval_time": 1.0395
    },
    {
        "step": 47,
        "LE_instances": 46,
        "LE_relative": 0.7666666666666674,
        "accuracy": 0.333333,
        "train_time": 0.7779,
        "eval_time": 1.0386
    },
    {
        "step": 48,
        "LE_instances": 47,
        "LE_relative": 0.7833333333333341,
        "accuracy": 0.333333,
        "train_time": 0.7809,
        "eval_time": 1.0293
    },
    {
        "step": 49,
        "LE_instances": 48,
        "LE_relative": 0.8000000000000008,
        "accuracy": 0.333333,
        "train_time": 0.7794,
        "eval_time": 0.9929
    },
    {
        "step": 50,
        "LE_instances": 49,
        "LE_relative": 0.8166666666666675,
        "accuracy": 0.316667,
        "train_time": 0.8422,
        "eval_time": 0.9885
    },
    {
        "step": 51,
        "LE_instances": 50,
        "LE_relative": 0.8333333333333343,
        "accuracy": 0.266667,
        "train_time": 0.7763,
        "eval_time": 0.997
    },
    {
        "step": 52,
        "LE_instances": 51,
        "LE_relative": 0.850000000000001,
        "accuracy": 0.233333,
        "train_time": 0.7834,
        "eval_time": 0.9696
    },
    {
        "step": 53,
        "LE_instances": 52,
        "LE_relative": 0.8666666666666677,
        "accuracy": 0.233333,
        "train_time": 0.7714,
        "eval_time": 1.0242
    },
    {
        "step": 54,
        "LE_instances": 53,
        "LE_relative": 0.8833333333333344,
        "accuracy": 0.166667,
        "train_time": 0.7874,
        "eval_time": 1.0082
    },
    {
        "step": 55,
        "LE_instances": 54,
        "LE_relative": 0.9000000000000011,
        "accuracy": 0.15,
        "train_time": 0.7697,
        "eval_time": 0.9838
    },
    {
        "step": 56,
        "LE_instances": 55,
        "LE_relative": 0.9166666666666679,
        "accuracy": 0.166667,
        "train_time": 0.7688,
        "eval_time": 0.9847
    },
    {
        "step": 57,
        "LE_instances": 56,
        "LE_relative": 0.9333333333333346,
        "accuracy": 0.166667,
        "train_time": 0.7648,
        "eval_time": 0.9883
    },
    {
        "step": 58,
        "LE_instances": 57,
        "LE_relative": 0.9500000000000013,
        "accuracy": 0.166667,
        "train_time": 0.8229,
        "eval_time": 0.9935
    },
    {
        "step": 59,
        "LE_instances": 58,
        "LE_relative": 0.966666666666668,
        "accuracy": 0.133333,
        "train_time": 0.7722,
        "eval_time": 1.0296
    },
    {
        "step": 60,
        "LE_instances": 59,
        "LE_relative": 0.9833333333333347,
        "accuracy": 0.133333,
        "train_time": 0.7786,
        "eval_time": 0.9699
    },
    {
        "step": 61,
        "LE_instances": 60,
        "LE_relative": 1.0000000000000013,
        "accuracy": 0.083333,
        "train_time": 0.7767,
        "eval_time": 1.009
    }
]